pyloan/__init__.py
pyloan/_day_count.py
pyloan/_enums.py
pyloan/_models.py
pyloan/_validators.py
pyloan/pyloan.py
pyloan-0.7.0.dist-info/licenses/LICENSE
pyloan-0.7.0.dist-info/METADATA
pyloan-0.7.0.dist-info/WHEEL
pyloan-0.7.0.dist-info/top_level.txt
pyloan-0.7.0.dist-info/RECORD
