Metadata-Version: 2.4
Name: pyloan
Version: 0.7.0
Summary: A package for mortgage/loan calculations.
Home-page: https://github.com/sudo-dakix/pyloan
Author: Darius Lesch, Da.Ki.X
Author-email: darius.lesch@proton.me, dakix@protonmail.com
Project-URL: Bug Tracker, https://github.com/sudo-dakix/pyloan/issues
Classifier: Programming Language :: Python :: 3
Classifier: License :: OSI Approved :: MIT License
Classifier: Operating System :: OS Independent
Requires-Python: >=3.6
License-File: LICENSE
Requires-Dist: python-dateutil
Dynamic: license-file
